{
    "cuda": null,
    "state": "running",
    "os": "Windows-10-10.0.18362-SP0",
    "python": "3.5.6",
    "docker": null,
    "args": [],
    "host": "DESKTOP-1RET8IC",
    "gpu_count": 1,
    "executable": "C:\\Users\\ST200423\\anaconda3\\envs\\pytorch\\python.exe",
    "username": "ST200423",
    "cpu_count": 8,
    "program": "train.py",
    "startedAt": "2020-12-06T23:33:57.747973",
    "gpu": "GeForce GTX 1060",
    "heartbeatAt": "2020-12-06T23:34:01.342067",
    "codePath": "train.py"
}
